git_batch_pull/__init__.py
git_batch_pull/cli/__init__.py
git_batch_pull/cli/commands.py
git_batch_pull/cli/health.py
git_batch_pull/cli/interface.py
git_batch_pull/config.py
git_batch_pull/core/__init__.py
git_batch_pull/core/batch_processor.py
git_batch_pull/core/health_check.py
git_batch_pull/core/protocol_handler.py
git_batch_pull/exceptions.py
git_batch_pull/git_ops.py
git_batch_pull/github_api.py
git_batch_pull/handlers/__init__.py
git_batch_pull/handlers/error_handler.py
git_batch_pull/handlers/logging_handler.py
git_batch_pull/main.py
git_batch_pull/models/__init__.py
git_batch_pull/models/config.py
git_batch_pull/models/repository.py
git_batch_pull/plugins/__init__.py
git_batch_pull/protocol_utils.py
git_batch_pull/protocol_warn.py
git_batch_pull/repo_store.py
git_batch_pull/security/__init__.py
git_batch_pull/security/credential_manager.py
git_batch_pull/security/path_validator.py
git_batch_pull/security/subprocess_runner.py
git_batch_pull/security/token_manager.py
git_batch_pull/services/__init__.py
git_batch_pull/services/container.py
git_batch_pull/services/git_service.py
git_batch_pull/services/github_service.py
git_batch_pull/services/repository_service.py
git_batch_pull/tests/__init__.py
git_batch_pull/utils.py
git_batch_pull-2.0.1.dist-info/LICENSE
git_batch_pull-2.0.1.dist-info/METADATA
git_batch_pull-2.0.1.dist-info/WHEEL
git_batch_pull-2.0.1.dist-info/entry_points.txt
git_batch_pull-2.0.1.dist-info/RECORD
