Metadata-Version: 2.3
Name: git-batch-pull
Version: 2.0.1
Summary: Clone and pull one, several, or all GitHub repos for a user/org, securely and robustly.
License: MIT
Keywords: git,github,batch,clone,pull,automation,devops,cli,repository,sync
Author: Al Diaz
Author-email: aldiazcode@gmail.com
Requires-Python: >=3.9.2,<4.0
Classifier: Development Status :: 5 - Production/Stable
Classifier: Environment :: Console
Classifier: Intended Audience :: Developers
Classifier: Intended Audience :: Information Technology
Classifier: Intended Audience :: System Administrators
Classifier: License :: OSI Approved :: MIT License
Classifier: Operating System :: MacOS
Classifier: Operating System :: Microsoft :: Windows
Classifier: Operating System :: OS Independent
Classifier: Operating System :: POSIX :: Linux
Classifier: Programming Language :: Python :: 3
Classifier: Programming Language :: Python :: 3.10
Classifier: Programming Language :: Python :: 3.11
Classifier: Programming Language :: Python :: 3.12
Classifier: Programming Language :: Python :: 3.13
Classifier: Programming Language :: Python :: 3 :: Only
Classifier: Programming Language :: Python :: 3.9
Classifier: Topic :: Software Development
Classifier: Topic :: Software Development :: Version Control
Classifier: Topic :: Software Development :: Version Control :: Git
Classifier: Topic :: System :: Archiving :: Backup
Classifier: Topic :: System :: Systems Administration
Classifier: Topic :: Utilities
Classifier: Typing :: Typed
Requires-Dist: argcomplete
Requires-Dist: colorama
Requires-Dist: cryptography (>=44.0.1)
Requires-Dist: docutils (>=0.20,<0.21)
Requires-Dist: importlib-metadata
Requires-Dist: keyring
Requires-Dist: python-dotenv
Requires-Dist: requests
Requires-Dist: tomli
Requires-Dist: tqdm
Requires-Dist: typer (>=0.15.0,<0.16.0)
Project-URL: Bug Tracker, https://github.com/alpersonalwebsite/git_batch_pull/issues
Project-URL: Changelog, https://github.com/alpersonalwebsite/git_batch_pull/blob/main/CHANGELOG.md
Project-URL: Contributing, https://github.com/alpersonalwebsite/git_batch_pull/blob/main/CONTRIBUTING.md
Project-URL: Documentation, https://github.com/alpersonalwebsite/git_batch_pull/blob/main/docs/
Project-URL: Homepage, https://github.com/alpersonalwebsite/git_batch_pull
Project-URL: Repository, https://github.com/alpersonalwebsite/git_batch_pull
Project-URL: Security, https://github.com/alpersonalwebsite/git_batch_pull/blob/main/SECURITY.md
Project-URL: Sponsor, https://github.com/sponsors/alpersonalwebsite
